mawo_slovnet/__init__.py
mawo_slovnet/model_downloader.py
mawo_slovnet/numpy_api.py
mawo_slovnet/numpy_inference.py
mawo_slovnet/numpy_loader.py
mawo_slovnet/slovnet_morph_news_v1.tar.neural.gz
mawo_slovnet/slovnet_ner_news_v1.tar.neural.gz
mawo_slovnet/slovnet_syntax_news_v1.tar.neural.gz
mawo_slovnet-1.0.7.dist-info/licenses/LICENSE
mawo_slovnet-1.0.7.dist-info/METADATA
mawo_slovnet-1.0.7.dist-info/WHEEL
mawo_slovnet-1.0.7.dist-info/top_level.txt
mawo_slovnet-1.0.7.dist-info/RECORD
