Metadata-Version: 2.4
Name: mawo-slovnet
Version: 1.0.7
Summary: Нейросетевые модели для русского языка: NER, морфология и синтаксис с автоматической загрузкой
Author-email: MAWO Team <team@mawo.ru>
Maintainer-email: MAWO Team <team@mawo.ru>
License: MIT
Project-URL: Homepage, https://github.com/mawo-ru/mawo-slovnet
Project-URL: Documentation, https://github.com/mawo-ru/mawo-slovnet#readme
Project-URL: Repository, https://github.com/mawo-ru/mawo-slovnet
Project-URL: Issues, https://github.com/mawo-ru/mawo-slovnet/issues
Project-URL: Changelog, https://github.com/mawo-ru/mawo-slovnet/blob/main/CHANGELOG.md
Keywords: nlp,russian,ner,morphology,syntax,slovnet,mawo
Classifier: Development Status :: 5 - Production/Stable
Classifier: Intended Audience :: Developers
Classifier: Intended Audience :: Science/Research
Classifier: License :: OSI Approved :: MIT License
Classifier: Natural Language :: Russian
Classifier: Operating System :: OS Independent
Classifier: Programming Language :: Python :: 3
Classifier: Programming Language :: Python :: 3.10
Classifier: Programming Language :: Python :: 3.11
Classifier: Programming Language :: Python :: 3.12
Classifier: Programming Language :: Python :: 3.13
Classifier: Topic :: Scientific/Engineering :: Artificial Intelligence
Classifier: Topic :: Text Processing :: Linguistic
Requires-Python: >=3.10
License-File: LICENSE
Requires-Dist: numpy>=1.20.0
Provides-Extra: dev
Requires-Dist: pytest>=7.0; extra == "dev"
Requires-Dist: black>=23.0; extra == "dev"
Requires-Dist: ruff>=0.1.0; extra == "dev"
Requires-Dist: mypy>=1.0; extra == "dev"
Provides-Extra: all
Requires-Dist: mawo-slovnet[dev]; extra == "all"
Dynamic: license-file
